{"dc74df761b0c6338b1d637bd211439bd":{"statistic":{"failed":0,"broken":0,"skipped":0,"passed":1,"unknown":0,"total":1},"items":[{"uid":"4ee86957b512c5d1","reportUrl":"https://ardominguez.github.io/fashionhub-web-automation/5//#testresult/4ee86957b512c5d1","status":"passed","time":{"start":1730063194636,"stop":1730063204222,"duration":9586}}]},"77645af2c52293c2fba42206c601ac85":{"statistic":{"failed":0,"broken":0,"skipped":0,"passed":1,"unknown":0,"total":1},"items":[{"uid":"4cc68fef03ebf1bb","reportUrl":"https://ardominguez.github.io/fashionhub-web-automation/5//#testresult/4cc68fef03ebf1bb","status":"passed","time":{"start":1730063192022,"stop":1730063198937,"duration":6915}}]},"6cc326e51d61197d7091093e1f5f18bd":{"statistic":{"failed":0,"broken":0,"skipped":0,"passed":1,"unknown":0,"total":1},"items":[{"uid":"b7cd5703aa476891","reportUrl":"https://ardominguez.github.io/fashionhub-web-automation/5//#testresult/b7cd5703aa476891","status":"passed","time":{"start":1730063155988,"stop":1730063195032,"duration":39044}}]},"db32fe29b55fa83dcadc934e691948d7":{"statistic":{"failed":0,"broken":0,"skipped":0,"passed":1,"unknown":0,"total":1},"items":[{"uid":"d5af7abc3266e26a","reportUrl":"https://ardominguez.github.io/fashionhub-web-automation/5//#testresult/d5af7abc3266e26a","status":"passed","time":{"start":1730063155990,"stop":1730063192913,"duration":36923}}]},"2026433043b02739357f3fa459e021ff":{"statistic":{"failed":0,"broken":0,"skipped":0,"passed":1,"unknown":0,"total":1},"items":[{"uid":"e944ec7fe2f5c874","reportUrl":"https://ardominguez.github.io/fashionhub-web-automation/5//#testresult/e944ec7fe2f5c874","status":"passed","time":{"start":1730063192940,"stop":1730063200094,"duration":7154}}]},"c889e6b71c190f7e058c294cf7c32ebe":{"statistic":{"failed":0,"broken":0,"skipped":0,"passed":1,"unknown":0,"total":1},"items":[{"uid":"c4a0b455df43d03c","reportUrl":"https://ardominguez.github.io/fashionhub-web-automation/5//#testresult/c4a0b455df43d03c","status":"passed","time":{"start":1730063195044,"stop":1730063201203,"duration":6159}}]},"eebd3b3bcd0dea0734ea1fee0760c904":{"statistic":{"failed":0,"broken":0,"skipped":0,"passed":1,"unknown":0,"total":1},"items":[{"uid":"d0887483dc9d2b19","reportUrl":"https://ardominguez.github.io/fashionhub-web-automation/5//#testresult/d0887483dc9d2b19","status":"passed","time":{"start":1730063155984,"stop":1730063191996,"duration":36012}}]},"cb3f33c1f40862b39088e5c70c6866b9":{"statistic":{"failed":0,"broken":0,"skipped":0,"passed":1,"unknown":0,"total":1},"items":[{"uid":"5f283f9bddd972d6","reportUrl":"https://ardominguez.github.io/fashionhub-web-automation/5//#testresult/5f283f9bddd972d6","status":"passed","time":{"start":1730063192009,"stop":1730063199260,"duration":7251}}]},"220f95a697eefaac80577232629bb532":{"statistic":{"failed":0,"broken":0,"skipped":0,"passed":1,"unknown":0,"total":1},"items":[{"uid":"db7c466d58abaac0","reportUrl":"https://ardominguez.github.io/fashionhub-web-automation/5//#testresult/db7c466d58abaac0","status":"passed","time":{"start":1730063192015,"stop":1730063194615,"duration":2600}}]},"58f4739fb2f568fb7f2b57a9677ec6fb":{"statistic":{"failed":1,"broken":0,"skipped":0,"passed":0,"unknown":0,"total":1},"items":[{"uid":"201e5de8feb1b334","reportUrl":"https://ardominguez.github.io/fashionhub-web-automation/5//#testresult/201e5de8feb1b334","status":"failed","statusDetails":"expected: <true> but was: <false>","time":{"start":1730063155994,"stop":1730063191822,"duration":35828}}]}}